[
  {
    "backcolor": "#333333",
    "name": "Modularo AZERTY 110%",
    "author": "Sikino",
    "switchMount": "cherry",
    "pcb": true
  },
  [
    {
      "x": 2.5,
      "c": "#b8a500"
    },
    "Esc",
    {
      "x": 1,
      "c": "#00ad11"
    },
    "F1",
    "F2",
    "F3",
    "F4",
    {
      "x": 0.5
    },
    "F5",
    "F6",
    "F7",
    "F8",
    {
      "x": 0.5
    },
    "F9",
    "F10",
    "F11",
    "F12",
    {
      "x": 0.25,
      "c": "#0096a6"
    },
    "PrtSc",
    "Scroll Lock",
    "Pause\nBreak"
  ],
  [
    {
      "y": -0.75,
      "x": 21.5,
      "c": "#cccccc",
      "t": "#ff0000\n#000000",
      "a": 5,
      "f2": 1,
      "d": true
    },
    "<i class='fa fa-circle'></i>\nNUM LOCK",
    {
      "t": "#800000\n#000000",
      "d": true
    },
    "<i class='fa fa-circle'></i>\nCAPS LOCK",
    {
      "d": true
    },
    "<i class='fa fa-circle'></i>\nSCROLL LOCK"
  ],
  [
    {
      "y": 0.25,
      "c": "#4700ff",
      "t": "#000000",
      "a": 4
    },
    "M1",
    "M6",
    {
      "x": 0.5,
      "c": "#c700a6",
      "a": 7
    },
    "²",
    {
      "c": "#006acc",
      "a": 4,
      "f": 3
    },
    "1\n&",
    {
      "f": 3
    },
    "2\né\n\n~",
    {
      "f": 3
    },
    "3\n\"\n\n\"",
    {
      "f": 3
    },
    "4\n'\n\n{",
    {
      "f": 3
    },
    "5\n(\n\n[",
    {
      "f": 3
    },
    "6\n-\n\n|",
    {
      "f": 3
    },
    "7\nè\n\n`",
    {
      "f": 3
    },
    "8\n_\n\n\\",
    {
      "f": 3
    },
    "9\nç\n\n^",
    {
      "f": 3
    },
    "0\nà\n\n@",
    {
      "c": "#c700a6",
      "f": 3
    },
    "°\n)",
    {
      "f": 3
    },
    "+\n=\n\n}",
    {
      "c": "#b8a500",
      "w2": 2
    },
    "Back Space",
    {
      "x": 1.25,
      "c": "#0096a6"
    },
    "Insert",
    "Home",
    "PgUp",
    {
      "x": 0.25,
      "c": "#11cf00"
    },
    "Num Lock",
    "/",
    "*",
    "-"
  ],
  [
    {
      "c": "#4700ff"
    },
    "M2",
    "M7",
    {
      "x": 0.5,
      "c": "#b8a500",
      "w": 1.5
    },
    "Tab",
    {
      "c": "#ba0000"
    },
    "A",
    "Z",
    "E",
    "R",
    "T",
    "Y",
    "U",
    "I",
    "O",
    "P",
    {
      "c": "#c700a6",
      "f": 3
    },
    "¨\n^",
    {
      "f": 3
    },
    "£\n$\n\n¤",
    {
      "x": 0.25,
      "c": "#b8a500",
      "w": 1.25,
      "h": 2,
      "w2": 1.5,
      "h2": 1,
      "x2": -0.25
    },
    "Enter",
    {
      "x": 0.25,
      "c": "#0096a6"
    },
    "Delete",
    "End",
    "PgDn",
    {
      "x": 0.25,
      "c": "#11cf00",
      "f": 3
    },
    "7\nHome",
    {
      "f": 3
    },
    "8\n↑",
    {
      "f": 3
    },
    "9\nPgUp",
    {
      "h": 2
    },
    "+"
  ],
  [
    {
      "c": "#4700ff"
    },
    "M3",
    "M8",
    {
      "x": 0.5,
      "c": "#b8a500",
      "w": 1.75
    },
    "Caps Lock",
    {
      "c": "#ba0000"
    },
    "Q",
    "S",
    "D",
    "F",
    "G",
    "H",
    "J",
    "K",
    "L",
    "M",
    {
      "c": "#c700a6",
      "f": 3
    },
    "%\nù",
    {
      "f": 3
    },
    "µ\n*",
    {
      "x": 4.75,
      "c": "#11cf00",
      "f": 3
    },
    "4\n←",
    "5",
    {
      "f": 3
    },
    "6\n→"
  ],
  [
    {
      "c": "#4700ff"
    },
    "M4",
    "M9",
    {
      "x": 0.5,
      "c": "#b8a500",
      "w": 2.25
    },
    "Shift",
    {
      "c": "#ba0000"
    },
    "W",
    "X",
    "C",
    "V",
    "B",
    "N",
    {
      "c": "#c700a6",
      "f": 3
    },
    "?\n,",
    {
      "f": 3
    },
    ".\n;",
    {
      "f": 3
    },
    "/\n:",
    {
      "f": 3
    },
    "§\n!",
    {
      "c": "#b8a500",
      "w": 2.75
    },
    "Shift",
    {
      "x": 1.25,
      "c": "#b56300"
    },
    "↑",
    {
      "x": 1.25,
      "c": "#11cf00",
      "f": 3
    },
    "1\nEnd",
    {
      "f": 3
    },
    "2\n↓",
    {
      "f": 3
    },
    "3\nPgDn",
    {
      "h": 2
    },
    "Enter"
  ],
  [
    {
      "c": "#4700ff"
    },
    "M5",
    "M10",
    {
      "x": 0.5,
      "c": "#b8a500",
      "w": 1.25
    },
    "Ctrl",
    {
      "w": 1.25
    },
    "Win",
    {
      "w": 1.25
    },
    "Alt",
    {
      "a": 7,
      "w": 6.25
    },
    "",
    {
      "a": 4,
      "w": 1.25
    },
    "Alt Gr",
    {
      "w": 1.25
    },
    "Fn",
    {
      "w": 1.25
    },
    "Win",
    {
      "w": 1.25
    },
    "Ctrl",
    {
      "x": 0.25,
      "c": "#b56300"
    },
    "←",
    "↓",
    "→",
    {
      "x": 0.25,
      "c": "#11cf00",
      "f": 3,
      "w": 2
    },
    "0\nIns",
    {
      "f": 3
    },
    ".\nDel"
  ]
]